ArchR_h5ad/__init__.py
ArchR_h5ad/_compose_adata/_add_obs_var.py
ArchR_h5ad/_compose_adata/_cleanup_anndata.py
ArchR_h5ad/_compose_adata/_compose_anndata.py
ArchR_h5ad/_compose_adata/_dict_to_adata.py
ArchR_h5ad/_compose_adata/_write_h5ad.py
ArchR_h5ad/_main/_Arrow.py
ArchR_h5ad/_main/_read_arrow_to_adata.py
ArchR_h5ad/_parse_arrow/_add_ArchR_metadata.py
ArchR_h5ad/_parse_arrow/_add_matrix_parameters.py
ArchR_h5ad/_parse_arrow/_read_arrow_chromosome.py
ArchR_h5ad/_utility_functions/_ordered_chromosomes.py
ArchR_h5ad-0.0.12.dist-info/LICENSE
ArchR_h5ad-0.0.12.dist-info/METADATA
ArchR_h5ad-0.0.12.dist-info/WHEEL
ArchR_h5ad-0.0.12.dist-info/top_level.txt
ArchR_h5ad-0.0.12.dist-info/RECORD
