Metadata-Version: 2.1
Name: ArchR-h5ad
Version: 0.0.12
Summary: ArchR_h5ad: Read .arrow files (from ArchR) to anndata.
Home-page: UNKNOWN
Author: Michael E. Vinyard - Harvard University - Massachussetts General Hospital - Broad Institute of MIT and Harvard
Author-email: mvinyard@broadinstitute.org
License: MIT
Platform: UNKNOWN
Classifier: Development Status :: 2 - Pre-Alpha
Classifier: Programming Language :: Python :: 3.6
Classifier: Intended Audience :: Science/Research
Classifier: Topic :: Scientific/Engineering :: Bio-Informatics
Requires-Python: >3.6.0
License-File: LICENSE
Requires-Dist: anndata (>=0.7.8)
Requires-Dist: licorice-font (>=0.0.3)
Requires-Dist: tqdm (>=4.64.0)
